distribute_setup.py
setup.cfg
setup.py
PQHelper.egg-info/PKG-INFO
PQHelper.egg-info/SOURCES.txt
PQHelper.egg-info/dependency_links.txt
PQHelper.egg-info/requires.txt
PQHelper.egg-info/top_level.txt
pqhelper/__init__.py
pqhelper/base.py
pqhelper/capture.py
pqhelper/easy.py
pqhelper/ui.py
pqhelper/versus.py
pqhelper/data/2.png
pqhelper/data/3.png
pqhelper/data/4.png
pqhelper/data/5.png
pqhelper/data/6.png
pqhelper/data/7.png
pqhelper/data/8.png
pqhelper/data/@.png
pqhelper/data/_.png
pqhelper/data/__init__.py
pqhelper/data/b.png
pqhelper/data/c.png
pqhelper/data/capture template 1280x960.png
pqhelper/data/extra action template.png
pqhelper/data/g.png
pqhelper/data/h.png
pqhelper/data/m.png
pqhelper/data/r.png
pqhelper/data/s.png
pqhelper/data/versus template 1280x960.png
pqhelper/data/x.png
pqhelper/data/y.png
tests/__init__.py
tests/execution_profiles/__init__.py
tests/execution_profiles/capture_profile.py
tests/integration/__init__.py
tests/integration/capture.png
tests/integration/test_base.py
tests/integration/test_capture.py
tests/integration/test_easy.py
tests/integration/test_versus.py
tests/integration/versus.png
tests/manual/__init__.py
tests/manual/capture_readme_confirmation.py
tests/manual/versus_readme_confirmation.py