Metadata-Version: 1.1
Name: PQHelper
Version: 0.1.2.3
Summary: Get advice on the game called Puzzle Quest.
Home-page: http://github.com/kobejohn/PQHelper
Author: KobeJohn
Author-email: niericentral@gmail.com
License: MIT
Platform: UNKNOWN
Classifier: Development Status :: 4 - Beta
Classifier: Environment :: Console
Classifier: Programming Language :: Python :: 2.7
